<annotation verified="yes">
    <folder>Annotation</folder>
    <filename>20210505_165907_frame_11900.jpg</filename>
    <path>Object-Tagging-PascalVOC-export/Annotations/20210505_165907_frame_11900.jpg</path>
    <source>
        <database>Unknown</database>
    </source>
    <size>
        <width>1280</width>
        <height>720</height>
        <depth>3</depth>
    </size>
    <segmented>0</segmented>
    <object>
    <name>motorcycle</name>
    <pose>Unspecified</pose>
    <truncated>0</truncated>
    <difficult>0</difficult>
    <bndbox>
        <xmin>821.6714477539062</xmin>
        <ymin>329.74875926971436</ymin>
        <xmax>851.083984375</xmax>
        <ymax>382.5946283340454</ymax>
    </bndbox>
</object>
</annotation>
