<annotation verified="yes">
    <folder>Annotation</folder>
    <filename>20210503_153255_frame_420.jpg</filename>
    <path>Object-Tagging-PascalVOC-export/Annotations/20210503_153255_frame_420.jpg</path>
    <source>
        <database>Unknown</database>
    </source>
    <size>
        <width>1280</width>
        <height>720</height>
        <depth>3</depth>
    </size>
    <segmented>0</segmented>
    <object>
    <name>person</name>
    <pose>Unspecified</pose>
    <truncated>0</truncated>
    <difficult>0</difficult>
    <bndbox>
        <xmin>824.4882121896098</xmin>
        <ymin>372.31805364943943</ymin>
        <xmax>872.8590312814067</xmax>
        <ymax>469.33393995620213</ymax>
    </bndbox>
</object><object>
    <name>other vehicles</name>
    <pose>Unspecified</pose>
    <truncated>0</truncated>
    <difficult>0</difficult>
    <bndbox>
        <xmin>815.6804255720731</xmin>
        <ymin>424.17193426042985</ymin>
        <xmax>905.1883439943141</xmax>
        <ymax>556.163735679067</ymax>
    </bndbox>
</object>
</annotation>
