<annotation verified="yes">
    <folder>Annotation</folder>
    <filename>20210505_173347_frame_12100.jpg</filename>
    <path>Object-Tagging-PascalVOC-export/Annotations/20210505_173347_frame_12100.jpg</path>
    <source>
        <database>Unknown</database>
    </source>
    <size>
        <width>1280</width>
        <height>720</height>
        <depth>3</depth>
    </size>
    <segmented>0</segmented>
    <object>
    <name>car</name>
    <pose>Unspecified</pose>
    <truncated>0</truncated>
    <difficult>0</difficult>
    <bndbox>
        <xmin>634.6712493896484</xmin>
        <ymin>324.2621397972107</ymin>
        <xmax>728.9806365966797</xmax>
        <ymax>398.2931900024414</ymax>
    </bndbox>
</object>
</annotation>
