<annotation verified="yes">
    <folder>Annotation</folder>
    <filename>20210503_153255_frame_21620.jpg</filename>
    <path>Object-Tagging-PascalVOC-export/Annotations/20210503_153255_frame_21620.jpg</path>
    <source>
        <database>Unknown</database>
    </source>
    <size>
        <width>1280</width>
        <height>720</height>
        <depth>3</depth>
    </size>
    <segmented>0</segmented>
    <object>
    <name>motorcycle</name>
    <pose>Unspecified</pose>
    <truncated>0</truncated>
    <difficult>0</difficult>
    <bndbox>
        <xmin>966.6260327391363</xmin>
        <ymin>393.61678323010284</ymin>
        <xmax>1093.2401074461677</xmax>
        <ymax>585.6112786219486</ymax>
    </bndbox>
</object><object>
    <name>person</name>
    <pose>Unspecified</pose>
    <truncated>0</truncated>
    <difficult>0</difficult>
    <bndbox>
        <xmin>984.3354655294953</xmin>
        <ymin>345.6352718078382</ymin>
        <xmax>1041.6488983653162</xmax>
        <ymax>531.3242730720607</ymax>
    </bndbox>
</object>
</annotation>
