<annotation verified="yes">
    <folder>Annotation</folder>
    <filename>20210505_165907_frame_23220.jpg</filename>
    <path>Object-Tagging-PascalVOC-export/Annotations/20210505_165907_frame_23220.jpg</path>
    <source>
        <database>Unknown</database>
    </source>
    <size>
        <width>1280</width>
        <height>720</height>
        <depth>3</depth>
    </size>
    <segmented>0</segmented>
    <object>
    <name>motorcycle</name>
    <pose>Unspecified</pose>
    <truncated>0</truncated>
    <difficult>0</difficult>
    <bndbox>
        <xmin>1027.0931058990761</xmin>
        <ymin>352.00695322376737</ymin>
        <xmax>1280</xmax>
        <ymax>643.2838179519595</ymax>
    </bndbox>
</object>
</annotation>
