<annotation verified="yes">
    <folder>Annotation</folder>
    <filename>20210501_150607_frame_2690.jpg</filename>
    <path>Object-Tagging-PascalVOC-export/Annotations/20210501_150607_frame_2690.jpg</path>
    <source>
        <database>Unknown</database>
    </source>
    <size>
        <width>1280</width>
        <height>720</height>
        <depth>3</depth>
    </size>
    <segmented>0</segmented>
    <object>
    <name>car</name>
    <pose>Unspecified</pose>
    <truncated>0</truncated>
    <difficult>0</difficult>
    <bndbox>
        <xmin>871.807560137457</xmin>
        <ymin>274.8135696821516</ymin>
        <xmax>1020.4810996563574</xmax>
        <ymax>396.28056234718827</ymax>
    </bndbox>
</object><object>
    <name>car</name>
    <pose>Unspecified</pose>
    <truncated>0</truncated>
    <difficult>0</difficult>
    <bndbox>
        <xmin>408.1924398625429</xmin>
        <ymin>293.29767726161367</ymin>
        <xmax>545.4295532646048</xmax>
        <ymax>351.390586797066</ymax>
    </bndbox>
</object>
</annotation>
