<annotation verified="yes">
    <folder>Annotation</folder>
    <filename>20210505_171959_frame_9920.jpg</filename>
    <path>Object-Tagging-PascalVOC-export/Annotations/20210505_171959_frame_9920.jpg</path>
    <source>
        <database>Unknown</database>
    </source>
    <size>
        <width>1280</width>
        <height>720</height>
        <depth>3</depth>
    </size>
    <segmented>0</segmented>
    <object>
    <name>motorcycle</name>
    <pose>Unspecified</pose>
    <truncated>0</truncated>
    <difficult>0</difficult>
    <bndbox>
        <xmin>878.3604240282685</xmin>
        <ymin>329.2179648241206</ymin>
        <xmax>930.8268551236749</xmax>
        <ymax>406.10238693467335</ymax>
    </bndbox>
</object><object>
    <name>motorcycle</name>
    <pose>Unspecified</pose>
    <truncated>0</truncated>
    <difficult>0</difficult>
    <bndbox>
        <xmin>986.0070671378091</xmin>
        <ymin>330.12248743718595</ymin>
        <xmax>1065.6113074204945</xmax>
        <ymax>426.9064070351759</ymax>
    </bndbox>
</object><object>
    <name>person</name>
    <pose>Unspecified</pose>
    <truncated>0</truncated>
    <difficult>0</difficult>
    <bndbox>
        <xmin>993.243816254417</xmin>
        <ymin>283.08731155778895</ymin>
        <xmax>1037.5689045936397</xmax>
        <ymax>431.4290201005025</ymax>
    </bndbox>
</object><object>
    <name>motorcycle</name>
    <pose>Unspecified</pose>
    <truncated>0</truncated>
    <difficult>0</difficult>
    <bndbox>
        <xmin>1110.8409893992932</xmin>
        <ymin>326.50439698492465</ymin>
        <xmax>1276.381625441696</xmax>
        <ymax>451.3285175879397</ymax>
    </bndbox>
</object>
</annotation>
