<annotation verified="yes">
    <folder>Annotation</folder>
    <filename>20210501_150607_frame_7880.jpg</filename>
    <path>Object-Tagging-PascalVOC-export/Annotations/20210501_150607_frame_7880.jpg</path>
    <source>
        <database>Unknown</database>
    </source>
    <size>
        <width>1280</width>
        <height>720</height>
        <depth>3</depth>
    </size>
    <segmented>0</segmented>
    <object>
    <name>motorcycle</name>
    <pose>Unspecified</pose>
    <truncated>0</truncated>
    <difficult>0</difficult>
    <bndbox>
        <xmin>851.2226148409894</xmin>
        <ymin>348.21293969849245</ymin>
        <xmax>926.303886925795</xmax>
        <ymax>450.42399497487435</ymax>
    </bndbox>
</object><object>
    <name>person</name>
    <pose>Unspecified</pose>
    <truncated>0</truncated>
    <difficult>0</difficult>
    <bndbox>
        <xmin>858.4593639575971</xmin>
        <ymin>299.36871859296485</ymin>
        <xmax>909.1166077738516</xmax>
        <ymax>412.4340452261307</ymax>
    </bndbox>
</object><object>
    <name>person</name>
    <pose>Unspecified</pose>
    <truncated>0</truncated>
    <difficult>0</difficult>
    <bndbox>
        <xmin>1146.1201413427561</xmin>
        <ymin>325.5998743718593</ymin>
        <xmax>1197.6819787985864</xmax>
        <ymax>493.84108040201005</ymax>
    </bndbox>
</object><object>
    <name>motorcycle</name>
    <pose>Unspecified</pose>
    <truncated>0</truncated>
    <difficult>0</difficult>
    <bndbox>
        <xmin>1110.8409893992932</xmin>
        <ymin>363.58982412060305</ymin>
        <xmax>1276.381625441696</xmax>
        <ymax>497.4591708542714</ymax>
    </bndbox>
</object>
</annotation>
