<annotation verified="yes">
    <folder>Annotation</folder>
    <filename>20210501_150607_frame_11160.jpg</filename>
    <path>Object-Tagging-PascalVOC-export/Annotations/20210501_150607_frame_11160.jpg</path>
    <source>
        <database>Unknown</database>
    </source>
    <size>
        <width>1280</width>
        <height>720</height>
        <depth>3</depth>
    </size>
    <segmented>0</segmented>
    <object>
    <name>person</name>
    <pose>Unspecified</pose>
    <truncated>0</truncated>
    <difficult>0</difficult>
    <bndbox>
        <xmin>817.2646048109965</xmin>
        <ymin>302.0996332518337</ymin>
        <xmax>852.4536082474226</xmax>
        <ymax>386.59841075794617</ymax>
    </bndbox>
</object>
</annotation>
