<annotation verified="yes">
    <folder>Annotation</folder>
    <filename>20210505_165907_frame_17340.jpg</filename>
    <path>Object-Tagging-PascalVOC-export/Annotations/20210505_165907_frame_17340.jpg</path>
    <source>
        <database>Unknown</database>
    </source>
    <size>
        <width>1280</width>
        <height>720</height>
        <depth>3</depth>
    </size>
    <segmented>0</segmented>
    <object>
    <name>car</name>
    <pose>Unspecified</pose>
    <truncated>0</truncated>
    <difficult>0</difficult>
    <bndbox>
        <xmin>664.7104644775391</xmin>
        <ymin>302.577166557312</ymin>
        <xmax>757.8546905517578</xmax>
        <ymax>396.27110481262207</ymax>
    </bndbox>
</object>
</annotation>
