<annotation verified="yes">
    <folder>Annotation</folder>
    <filename>20210505_173347_frame_13920.jpg</filename>
    <path>Object-Tagging-PascalVOC-export/Annotations/20210505_173347_frame_13920.jpg</path>
    <source>
        <database>Unknown</database>
    </source>
    <size>
        <width>1280</width>
        <height>720</height>
        <depth>3</depth>
    </size>
    <segmented>0</segmented>
    <object>
    <name>car</name>
    <pose>Unspecified</pose>
    <truncated>0</truncated>
    <difficult>0</difficult>
    <bndbox>
        <xmin>617.4823760986328</xmin>
        <ymin>335.65927505493164</ymin>
        <xmax>699.7843170166016</xmax>
        <ymax>393.3727741241455</ymax>
    </bndbox>
</object><object>
    <name>car</name>
    <pose>Unspecified</pose>
    <truncated>0</truncated>
    <difficult>0</difficult>
    <bndbox>
        <xmin>458.1474304199219</xmin>
        <ymin>333.13456535339355</ymin>
        <xmax>542.9421234130859</xmax>
        <ymax>407.730188369751</ymax>
    </bndbox>
</object><object>
    <name>car</name>
    <pose>Unspecified</pose>
    <truncated>0</truncated>
    <difficult>0</difficult>
    <bndbox>
        <xmin>0</xmin>
        <ymin>0</ymin>
        <xmax>395.3074204946996</xmax>
        <ymax>601.4792713567839</ymax>
    </bndbox>
</object>
</annotation>
