<annotation verified="yes">
    <folder>Annotation</folder>
    <filename>VID_20210429_144011_frame_48940.jpg</filename>
    <path>Object-Tagging-PascalVOC-export/Annotations/VID_20210429_144011_frame_48940.jpg</path>
    <source>
        <database>Unknown</database>
    </source>
    <size>
        <width>1280</width>
        <height>720</height>
        <depth>3</depth>
    </size>
    <segmented>0</segmented>
    <object>
    <name>motorcycle</name>
    <pose>Unspecified</pose>
    <truncated>0</truncated>
    <difficult>0</difficult>
    <bndbox>
        <xmin>998.8912579957351</xmin>
        <ymin>381.1346396965866</ymin>
        <xmax>1118.976545842217</xmax>
        <ymax>531.5802781289507</ymax>
    </bndbox>
</object>
</annotation>
