<annotation verified="yes">
    <folder>Annotation</folder>
    <filename>VID_20210429_144011_frame_47720.jpg</filename>
    <path>Object-Tagging-PascalVOC-export/Annotations/VID_20210429_144011_frame_47720.jpg</path>
    <source>
        <database>Unknown</database>
    </source>
    <size>
        <width>1280</width>
        <height>720</height>
        <depth>3</depth>
    </size>
    <segmented>0</segmented>
    <object>
    <name>other vehicles</name>
    <pose>Unspecified</pose>
    <truncated>0</truncated>
    <difficult>0</difficult>
    <bndbox>
        <xmin>1175.4270270173902</xmin>
        <ymin>317.5140950265898</ymin>
        <xmax>1211.9190314119214</xmax>
        <ymax>355.2975365701689</ymax>
    </bndbox>
</object><object>
    <name>car</name>
    <pose>Unspecified</pose>
    <truncated>0</truncated>
    <difficult>0</difficult>
    <bndbox>
        <xmin>1143.6426116838488</xmin>
        <ymin>266.01161369193153</ymin>
        <xmax>1194.6666666666667</xmax>
        <ymax>327.6253056234719</ymax>
    </bndbox>
</object>
</annotation>
