<annotation verified="yes">
    <folder>Annotation</folder>
    <filename>VID_20210430_155115_frame_5940.jpg</filename>
    <path>Object-Tagging-PascalVOC-export/Annotations/VID_20210430_155115_frame_5940.jpg</path>
    <source>
        <database>Unknown</database>
    </source>
    <size>
        <width>1280</width>
        <height>720</height>
        <depth>3</depth>
    </size>
    <segmented>0</segmented>
    <object>
    <name>person</name>
    <pose>Unspecified</pose>
    <truncated>0</truncated>
    <difficult>0</difficult>
    <bndbox>
        <xmin>553.9903514817368</xmin>
        <ymin>267.43566176470586</ymin>
        <xmax>575.1619572708477</xmax>
        <ymax>311.5533088235294</ymax>
    </bndbox>
</object>
</annotation>
