<annotation verified="yes">
    <folder>Annotation</folder>
    <filename>VID_20210429_144011_frame_14910.jpg</filename>
    <path>Object-Tagging-PascalVOC-export/Annotations/VID_20210429_144011_frame_14910.jpg</path>
    <source>
        <database>Unknown</database>
    </source>
    <size>
        <width>1280</width>
        <height>720</height>
        <depth>3</depth>
    </size>
    <segmented>0</segmented>
    <object>
    <name>car</name>
    <pose>Unspecified</pose>
    <truncated>0</truncated>
    <difficult>0</difficult>
    <bndbox>
        <xmin>587.0812720848056</xmin>
        <ymin>340.97675879396985</ymin>
        <xmax>621.4558303886926</xmax>
        <ymax>372.6350502512563</ymax>
    </bndbox>
</object>
</annotation>
