<annotation verified="yes">
    <folder>Annotation</folder>
    <filename>VID_20210429_155708_frame_6860.jpg</filename>
    <path>Object-Tagging-PascalVOC-export/Annotations/VID_20210429_155708_frame_6860.jpg</path>
    <source>
        <database>Unknown</database>
    </source>
    <size>
        <width>1280</width>
        <height>720</height>
        <depth>3</depth>
    </size>
    <segmented>0</segmented>
    <object>
    <name>motorcycle</name>
    <pose>Unspecified</pose>
    <truncated>0</truncated>
    <difficult>0</difficult>
    <bndbox>
        <xmin>818.4166717529297</xmin>
        <ymin>318.391959798995</ymin>
        <xmax>883.7879858657244</xmax>
        <ymax>430.3119421005249</ymax>
    </bndbox>
</object>
</annotation>
