<annotation verified="yes">
    <folder>Annotation</folder>
    <filename>VID_20210429_144011_frame_48880.jpg</filename>
    <path>Object-Tagging-PascalVOC-export/Annotations/VID_20210429_144011_frame_48880.jpg</path>
    <source>
        <database>Unknown</database>
    </source>
    <size>
        <width>1280</width>
        <height>720</height>
        <depth>3</depth>
    </size>
    <segmented>0</segmented>
    <object>
    <name>car</name>
    <pose>Unspecified</pose>
    <truncated>0</truncated>
    <difficult>0</difficult>
    <bndbox>
        <xmin>847.8749111584932</xmin>
        <ymin>330.16118836915297</ymin>
        <xmax>1027.093105899076</xmax>
        <ymax>412.082806573957</ymax>
    </bndbox>
</object>
</annotation>
