<annotation verified="yes">
    <folder>Annotation</folder>
    <filename>VID_20210502_174603_frame_11130.jpg</filename>
    <path>Object-Tagging-PascalVOC-export/Annotations/VID_20210502_174603_frame_11130.jpg</path>
    <source>
        <database>Unknown</database>
    </source>
    <size>
        <width>1280</width>
        <height>720</height>
        <depth>3</depth>
    </size>
    <segmented>0</segmented>
    <object>
    <name>person</name>
    <pose>Unspecified</pose>
    <truncated>0</truncated>
    <difficult>0</difficult>
    <bndbox>
        <xmin>62.82573152960999</xmin>
        <ymin>269.2800256545866</ymin>
        <xmax>226.52452025586354</xmax>
        <ymax>625.3350189633376</ymax>
    </bndbox>
</object><object>
    <name>person</name>
    <pose>Unspecified</pose>
    <truncated>0</truncated>
    <difficult>0</difficult>
    <bndbox>
        <xmin>563.6604269498108</xmin>
        <ymin>277.0170430407663</ymin>
        <xmax>610.2907522671936</xmax>
        <ymax>355.66432516433196</ymax>
    </bndbox>
</object><object>
    <name>car</name>
    <pose>Unspecified</pose>
    <truncated>0</truncated>
    <difficult>0</difficult>
    <bndbox>
        <xmin>944.0377807617188</xmin>
        <ymin>236.73250296625272</ymin>
        <xmax>1280</xmax>
        <ymax>455.2993641189017</ymax>
    </bndbox>
</object><object>
    <name>motorcycle</name>
    <pose>Unspecified</pose>
    <truncated>0</truncated>
    <difficult>0</difficult>
    <bndbox>
        <xmin>624.9813501972125</xmin>
        <ymin>319.2658756867372</ymin>
        <xmax>667.8562967914507</xmax>
        <ymax>372.55902992639176</ymax>
    </bndbox>
</object><object>
    <name>motorcycle</name>
    <pose>Unspecified</pose>
    <truncated>0</truncated>
    <difficult>0</difficult>
    <bndbox>
        <xmin>551.9380729962683</xmin>
        <ymin>329.48546986212176</ymin>
        <xmax>620.2944725324011</xmax>
        <ymax>417.0100913487856</ymax>
    </bndbox>
</object><object>
    <name>person</name>
    <pose>Unspecified</pose>
    <truncated>0</truncated>
    <difficult>0</difficult>
    <bndbox>
        <xmin>895.0428410294891</xmin>
        <ymin>269.8464568737334</ymin>
        <xmax>937.4149723771453</xmax>
        <ymax>339.3413337353057</ymax>
    </bndbox>
</object><object>
    <name>person</name>
    <pose>Unspecified</pose>
    <truncated>0</truncated>
    <difficult>0</difficult>
    <bndbox>
        <xmin>761.2465828229282</xmin>
        <ymin>280.7644024901987</ymin>
        <xmax>809.6439522076938</xmax>
        <ymax>398.685208596713</ymax>
    </bndbox>
</object><object>
    <name>person</name>
    <pose>Unspecified</pose>
    <truncated>0</truncated>
    <difficult>0</difficult>
    <bndbox>
        <xmin>725.9701492537313</xmin>
        <ymin>287.37989886219975</ymin>
        <xmax>759.6304193319118</xmax>
        <ymax>431.1978508217446</ymax>
    </bndbox>
</object><object>
    <name>motorcycle</name>
    <pose>Unspecified</pose>
    <truncated>0</truncated>
    <difficult>0</difficult>
    <bndbox>
        <xmin>685.9417199715707</xmin>
        <ymin>328.3407079646018</ymin>
        <xmax>816.9438521677328</xmax>
        <ymax>424.82616940581545</ymax>
    </bndbox>
</object><object>
    <name>motorcycle</name>
    <pose>Unspecified</pose>
    <truncated>0</truncated>
    <difficult>0</difficult>
    <bndbox>
        <xmin>282.92821606254444</xmin>
        <ymin>302.853982300885</ymin>
        <xmax>339.33191186922534</xmax>
        <ymax>397.51896333754746</ymax>
    </bndbox>
</object><object>
    <name>motorcycle</name>
    <pose>Unspecified</pose>
    <truncated>0</truncated>
    <difficult>0</difficult>
    <bndbox>
        <xmin>413.9303482587065</xmin>
        <ymin>328.3407079646018</ymin>
        <xmax>450.31982942430704</xmax>
        <ymax>409.3520859671302</ymax>
    </bndbox>
</object><object>
    <name>car</name>
    <pose>Unspecified</pose>
    <truncated>0</truncated>
    <difficult>0</difficult>
    <bndbox>
        <xmin>464.8756218905473</xmin>
        <ymin>301.03350189633375</ymin>
        <xmax>542.2032693674485</xmax>
        <ymax>367.4810366624526</ymax>
    </bndbox>
</object><object>
    <name>person</name>
    <pose>Unspecified</pose>
    <truncated>0</truncated>
    <difficult>0</difficult>
    <bndbox>
        <xmin>161.0234541577825</xmin>
        <ymin>257.34197218710494</ymin>
        <xmax>211.9687277896233</xmax>
        <ymax>397.51896333754746</ymax>
    </bndbox>
</object><object>
    <name>motorcycle</name>
    <pose>Unspecified</pose>
    <truncated>0</truncated>
    <difficult>0</difficult>
    <bndbox>
        <xmin>812.3951670220326</xmin>
        <ymin>304.67446270543616</ymin>
        <xmax>856.0625444207533</xmax>
        <ymax>390.23704171934264</ymax>
    </bndbox>
</object>
</annotation>
