<annotation verified="yes">
    <folder>Annotation</folder>
    <filename>VID_20210429_144011_frame_16210.jpg</filename>
    <path>Object-Tagging-PascalVOC-export/Annotations/VID_20210429_144011_frame_16210.jpg</path>
    <source>
        <database>Unknown</database>
    </source>
    <size>
        <width>1280</width>
        <height>720</height>
        <depth>3</depth>
    </size>
    <segmented>0</segmented>
    <object>
    <name>motorcycle</name>
    <pose>Unspecified</pose>
    <truncated>0</truncated>
    <difficult>0</difficult>
    <bndbox>
        <xmin>850.3180212014134</xmin>
        <ymin>370.82600502512565</ymin>
        <xmax>926.303886925795</xmax>
        <ymax>492.0320351758794</ymax>
    </bndbox>
</object>
</annotation>
